wolfsoftware/baseline_package_importable/__init__.py
wolfsoftware/baseline_package_importable/exceptions.py
wolfsoftware/baseline_package_importable/functions.py
wolfsoftware.baseline_package_importable-0.1.0.dist-info/LICENSE.md
wolfsoftware.baseline_package_importable-0.1.0.dist-info/METADATA
wolfsoftware.baseline_package_importable-0.1.0.dist-info/WHEEL
wolfsoftware.baseline_package_importable-0.1.0.dist-info/top_level.txt
wolfsoftware.baseline_package_importable-0.1.0.dist-info/RECORD
