Metadata-Version: 2.1
Name: wolfsoftware.baseline-package-importable
Version: 0.1.0
Summary: A basic package template for importable packages.
Home-page: https://github.com/GitHubToolbox/baseline-package-importable
Author: Wolf Software
Author-email: pypi@wolfsoftware.com
License: MIT
Project-URL: Source, https://github.com/GitHubToolbox/baseline-package-importable
Project-URL: Tracker, https://github.com/GitHubToolbox/baseline-package-importable/issues/
Project-URL: Documentation, https://github.com/GitHubToolbox/baseline-package-importable
Project-URL: Sponsor, https://github.com/sponsors/WolfSoftware
Keywords: python,template
Classifier: Development Status :: 4 - Beta
Classifier: Environment :: Console
Classifier: Intended Audience :: Developers
Classifier: License :: OSI Approved :: MIT License
Classifier: Programming Language :: Python :: 3
Classifier: Programming Language :: Python :: 3.9
Classifier: Programming Language :: Python :: 3.10
Classifier: Programming Language :: Python :: 3.11
Classifier: Programming Language :: Python :: 3.12
Classifier: Operating System :: OS Independent
Classifier: Topic :: Software Development
Requires-Python: >=3.9
License-File: LICENSE.md
Requires-Dist: pytest ==8.2.1
Requires-Dist: setuptools ==70.0.0
